crf_pos/__init__.py
crf_pos/api.py
crf_pos/normalization/__init__.py
crf_pos/normalization/normalizer.py
crf_pos/normalization/tokenizer.py
crf_pos/pos_tagger/__init__.py
crf_pos/pos_tagger/crf.py
crf_pos/pos_tagger/meta_tagger.py
crf_pos/pos_tagger/utils.py
crf_pos/pos_tagger/wapiti.py
crf_pos-2.2.2.dist-info/LICENSE
crf_pos-2.2.2.dist-info/METADATA
crf_pos-2.2.2.dist-info/WHEEL
crf_pos-2.2.2.dist-info/top_level.txt
crf_pos-2.2.2.dist-info/RECORD
