Metadata-Version: 2.1
Name: crf-pos
Version: 2.2.2
Summary: Persian Part-of-Speech tagger framework
Home-page: https://github.com/MohammadForouhesh/crf-pos-persian
Author: MohammadForouhesh
Author-email: Mohammadh.Forouhesh@gmail.com
License: MIT
Keywords: NLP,POS
Platform: UNKNOWN
Classifier: License :: OSI Approved :: MIT License
Classifier: Programming Language :: Python :: 3
Classifier: Programming Language :: Python :: 3.7
Classifier: Programming Language :: Python :: 3.8
Classifier: Programming Language :: Python :: 3.9
Requires-Python: >=3.7
License-File: LICENSE
Requires-Dist: nltk (>=3.6.6)
Requires-Dist: setuptools (>=58.0.4)
Requires-Dist: scikit-learn (>=1.0.2)
Requires-Dist: sklearn-crfsuite (>=0.3.6)
Requires-Dist: requests (>=2.26.0)
Requires-Dist: libwapiti (>=0.2.1)
Requires-Dist: pytest (>=6.2.5)
Requires-Dist: coverage (>=6.2)
